django_templated_mail-1.1.0.dist-info/DESCRIPTION.rst
django_templated_mail-1.1.0.dist-info/METADATA
django_templated_mail-1.1.0.dist-info/RECORD
django_templated_mail-1.1.0.dist-info/WHEEL
django_templated_mail-1.1.0.dist-info/metadata.json
django_templated_mail-1.1.0.dist-info/top_level.txt
templated_mail/__init__.py
templated_mail/mail.py
